dspeech/__init__.py
dspeech/base_handler.py
dspeech/cli.py
dspeech/stt.py
dspeech/tts.py
dspeech/utils.py
dspeech/version.py
dspeech/f5tts/__init__.py
dspeech/f5tts/f5api.py
dspeech/f5tts/model/__init__.py
dspeech/f5tts/model/cfm.py
dspeech/f5tts/model/dataset.py
dspeech/f5tts/model/ecapa_tdnn.py
dspeech/f5tts/model/modules.py
dspeech/f5tts/model/trainer.py
dspeech/f5tts/model/utils.py
dspeech/silero_vad/__init__.py
dspeech/silero_vad/vad_model.py
dspeech/whisper/__init__.py
dspeech/whisper/model.py
dspeech-0.1.2.dist-info/LICENSE
dspeech-0.1.2.dist-info/METADATA
dspeech-0.1.2.dist-info/WHEEL
dspeech-0.1.2.dist-info/entry_points.txt
dspeech-0.1.2.dist-info/top_level.txt
dspeech-0.1.2.dist-info/RECORD
