Metadata-Version: 2.1
Name: dspeech
Version: 0.1.2
Summary: A Speech-to-Text toolkit with VAD, punctuation, and emotion classification
Home-page: https://gitee.com/iint/dspeech
Author: Zhao Sheng
Author-email: zhaosheng@nuaa.edu.cn
Keywords: speech-to-text,speech processing,speech recognition,speech synthesis,speech
Classifier: Programming Language :: Python :: 3
Classifier: License :: OSI Approved :: MIT License
Classifier: Operating System :: OS Independent
Requires-Python: >=3.10
License-File: LICENSE
Requires-Dist: torch ==2.1.2
Requires-Dist: torchaudio ==2.1.2
Requires-Dist: torchvision ==0.16.2
Requires-Dist: funasr ==1.1.12
Requires-Dist: faster-whisper ==1.0.3
Requires-Dist: webrtcvad ==2.0.10
Requires-Dist: silero-vad-nuaazs ==0.0.4
Requires-Dist: numpy
Requires-Dist: soundfile
Requires-Dist: rich
Requires-Dist: click
Provides-Extra: conversion
Requires-Dist: transformers[torch] >=4.23 ; extra == 'conversion'
Provides-Extra: dev
Requires-Dist: black ==23.* ; extra == 'dev'
Requires-Dist: flake8 ==6.* ; extra == 'dev'
Requires-Dist: isort ==5.* ; extra == 'dev'
Requires-Dist: pytest ==7.* ; extra == 'dev'
